README.rst
setup.cfg
setup.py
numbamisc/__init__.py
numbamisc/_median_filter.py
numbamisc.egg-info/PKG-INFO
numbamisc.egg-info/SOURCES.txt
numbamisc.egg-info/dependency_links.txt
numbamisc.egg-info/not-zip-safe
numbamisc.egg-info/requires.txt
numbamisc.egg-info/top_level.txt