Metadata-Version: 1.1
Name: numbamisc
Version: 0.0.1
Summary: Miscellaneous utilities based on numba and jinja.
Home-page: https://github.com/MSeifert04/numbamisc
Author: Michael Seifert
Author-email: michaelseifert04@yahoo.de
License: Apache License Version 2.0
Keywords: convolution filter median numba
Platform: all
Classifier: Development Status :: 4 - Beta
Classifier: Programming Language :: Python :: 2
Classifier: Programming Language :: Python :: 2.7
Classifier: Programming Language :: Python :: 3
Classifier: Programming Language :: Python :: 3.3
Classifier: Programming Language :: Python :: 3.4
Classifier: Programming Language :: Python :: 3.5
Classifier: Programming Language :: Python :: 3.6
